ws_sim868/__init__.py
ws_sim868/modemUnit.py
ws_sim868-1.0.0b8.dist-info/licenses/LICENSE.txt
ws_sim868-1.0.0b8.dist-info/METADATA
ws_sim868-1.0.0b8.dist-info/WHEEL
ws_sim868-1.0.0b8.dist-info/top_level.txt
ws_sim868-1.0.0b8.dist-info/RECORD
