Metadata-Version: 2.4
Name: ws_sim868
Version: 1.0.0b8
Summary: Python package to control the Waveshare GSM/GPRS/GNSS Pi HAT
Home-page: https://github.com/matthewnaruzny/ws_sim868
Author: Matthew Naruzny
Author-email: software@mnaruzny.com
Project-URL: Bug Tracker, https://github.com/matthewnaruzny/ws_sim868/issues
Project-URL: Repository, https://github.com/matthewnaruzny/ws_sim868
Project-URL: Documentation, https://matthewnaruzny.github.io/ws_sim868/ws_sim868/modemUnit.html
Classifier: Programming Language :: Python :: 3.9
Classifier: Operating System :: OS Independent
Classifier: Development Status :: 4 - Beta
Requires-Python: >=3.9
License-File: LICENSE.txt
Dynamic: license-file
